{"cameraMode":{"drawMode":0,"name":"Shaded","section":"Shading Mode"},"sceneLighting":false,"audioPlay":false,"sceneViewState":{"showFog":true,"showMaterialUpdate":false,"showSkybox":false,"showFlares":true,"showImageEffects":true,"showParticleSystems":true},"in2DMode":false,"pivot":{"x":3.8393378257751467,"y":0.7689505219459534,"z":0.05725288391113281},"rotation":{"x":0.028832273557782174,"y":-0.9553336501121521,"z":0.2767803966999054,"w":0.09951711446046829},"size":0.6623402833938599,"orthographic":false}